MANIFEST.in
README.md
setup.py
examples/pdb_dump.py
examples/pdb_get_syscall_table.py
examples/pdb_lookup.py
examples/pdb_print_ctypes.py
examples/pdb_print_gvars.py
examples/pdb_print_tpi.py
examples/pdb_tpi_vtypes.py
examples/symchk.py
pdbparse/__init__.py
pdbparse/dbgold.py
pdbparse/dbi.py
pdbparse/fpo.py
pdbparse/gdata.py
pdbparse/info.py
pdbparse/omap.py
pdbparse/pe.py
pdbparse/peinfo.py
pdbparse/postfix_eval.py
pdbparse/symlookup.py
pdbparse/tpi.py
pdbparse/undecorate.py
pdbparse/undname.py
pdbparse.egg-info/PKG-INFO
pdbparse.egg-info/SOURCES.txt
pdbparse.egg-info/dependency_links.txt
pdbparse.egg-info/requires.txt
pdbparse.egg-info/top_level.txt
src/undname.c
src/undname.h
src/undname_py.c