Metadata-Version: 2.1
Name: pdbparse
Version: 1.5
Summary: Python parser for Microsoft PDB files
Home-page: https://github.com/moyix/pdbparse/
Author: Brendan Dolan-Gavitt
Author-email: brendandg@gatech.edu
License: UNKNOWN
Platform: UNKNOWN
Classifier: License :: OSI Approved :: GNU General Public License (GPL)
Classifier: Operating System :: OS Independent
